{
  "collectionName": "components_general_three_image_layouts",
  "info": {
    "name": "three image layout",
    "icon": "border-all"
  },
  "options": {},
  "attributes": {
    "images": {
      "collection": "file",
      "via": "related",
      "allowedTypes": [
        "images",
        "files",
        "videos"
      ],
      "plugin": "upload",
      "required": false
    },
    "featured_position": {
      "type": "enumeration",
      "enum": [
        "top",
        "right",
        "bottom",
        "left"
      ]
    }
  }
}
